pitot/__init__.py
pitot/aero.py
pitot/airac.py
pitot/geodesy.py
pitot/geodesy.pyi
pitot/isa.py
pitot/py.typed
pitot-0.3.2.dist-info/METADATA
pitot-0.3.2.dist-info/WHEEL
pitot-0.3.2.dist-info/RECORD
