Metadata-Version: 2.3
Name: pitot
Version: 0.3.2
Summary: Toolbox for aeronautic units and conversions
Author-email: Xavier Olive <git@xoolive.org>, Junzi Sun <j.sun-1@tudelft.nl>
License: MIT
Classifier: Development Status :: 5 - Production/Stable
Classifier: Intended Audience :: Information Technology
Classifier: Intended Audience :: Science/Research
Classifier: License :: OSI Approved :: MIT License
Classifier: Operating System :: MacOS
Classifier: Operating System :: Microsoft :: Windows
Classifier: Operating System :: POSIX :: Linux
Classifier: Programming Language :: Python :: 3
Classifier: Programming Language :: Python :: 3.8
Classifier: Programming Language :: Python :: 3.9
Classifier: Programming Language :: Python :: 3.10
Classifier: Topic :: Software Development :: Libraries
Classifier: Typing :: Typed
Requires-Python: >=3.9
Requires-Dist: impunity>=1.0.5
Requires-Dist: numpy>=2.0.2; python_version < '3.10'
Requires-Dist: numpy>=2.1.3; python_version >= '3.10'
Requires-Dist: pandas>=2.2.3
Requires-Dist: pyproj<3.7.1; python_version < '3.10'
Requires-Dist: pyproj>=3.7.0; python_version >= '3.10'
Requires-Dist: typing-extensions>=4.12.2
